pycommoncrawl/__init__.py
pycommoncrawl/common_crawl_data_accessor.py
pycommoncrawl/utils.py
pycommoncrawl/version_getter.py
pycommoncrawl/warc_string_record.py
pycommoncrawl-0.2.dist-info/METADATA
pycommoncrawl-0.2.dist-info/WHEEL
pycommoncrawl-0.2.dist-info/top_level.txt
pycommoncrawl-0.2.dist-info/RECORD
