Metadata-Version: 2.1
Name: pycommoncrawl
Version: 0.2
Summary: An interface to access common crawl data
Home-page: https://github.com/Aunsiels/pycommoncrawl
Author: Julien Romero
Author-email: romerojulien34@gmail.com
License: UNKNOWN
Platform: UNKNOWN
Classifier: Programming Language :: Python :: 3
Classifier: License :: OSI Approved :: MIT License
Classifier: Operating System :: OS Independent
Requires-Dist: progressbar
Requires-Dist: pytest
Requires-Dist: warc3-wet
